{
    "question-type": "multiple_one_solution",
    "title": "Wie wichtig sind Mischkulturen (und die Integration verschiedener Elemente) für Ihren Betrieb?",
    "choices": [
        {
            "Überhaupt nicht": 0
        },
        {
            "Ein wenig": 2.5
        },
        {
            "Mittelmäßig": 5
        },
        {
            "Ziemlich": 7.5
        },
        {
            "Sehr": 10
        }
    ],
    "scoring": "by-value",
    "mandatory": true,
    "scoring-type": "importance"
}